vitivinicultura_flask_api/__init__.py
vitivinicultura_flask_api/core.py
vitivinicultura_flask_api/utils.py
vitivinicultura_flask_api_package-1.0.0.dist-info/METADATA
vitivinicultura_flask_api_package-1.0.0.dist-info/WHEEL
vitivinicultura_flask_api_package-1.0.0.dist-info/top_level.txt
vitivinicultura_flask_api_package-1.0.0.dist-info/RECORD
