Metadata-Version: 2.4
Name: vitivinicultura_flask_api-package
Version: 1.0.0
Summary: Descricao da sua lib vitivinicultura_flask_api
Home-page: https://github.com/ordepzero/vitivinicultura_flask_api
Author: Pedro Ulisses
Author-email: ulissesph@gmail.com
License: MIT
Dynamic: author
Dynamic: author-email
Dynamic: description
Dynamic: description-content-type
Dynamic: home-page
Dynamic: license
Dynamic: summary
